setup.py
youzan/__init__.py
youzan.egg-info/PKG-INFO
youzan.egg-info/SOURCES.txt
youzan.egg-info/dependency_links.txt
youzan.egg-info/not-zip-safe
youzan.egg-info/pbr.json
youzan.egg-info/requires.txt
youzan.egg-info/top_level.txt