Metadata-Version: 1.1
Name: youzan
Version: 0.1.3
Summary: Youzan SDK for Python
Home-page: https://github.com/fengluo/youzan
Author: fengluo
Author-email: fengluo17@gmail.com
License: MIT
Platform: UNKNOWN
Classifier: Environment :: Web Environment
Classifier: Intended Audience :: Developers
Classifier: License :: OSI Approved :: MIT License
Classifier: Operating System :: OS Independent
Classifier: Programming Language :: Python
Classifier: Topic :: Internet :: WWW/HTTP :: Dynamic Content
Classifier: Topic :: Software Development :: Libraries :: Python Modules
